pdoc_prep/__init__.py
pdoc_prep/pdoc_prep.py
pdoc_prep/test_doc.py
pdoc_prep/test_pdoc_prep.py
pdoc_prep-0.0.4.data/scripts/pdoc_run
pdoc_prep-0.0.4.dist-info/METADATA
pdoc_prep-0.0.4.dist-info/WHEEL
pdoc_prep-0.0.4.dist-info/top_level.txt
pdoc_prep-0.0.4.dist-info/RECORD
