Metadata-Version: 2.1
Name: pdoc-prep
Version: 0.0.4
Summary: Add processing of sphinx-like docstring specs to pdoc via preprocessor.
Home-page: https://github.com/paepcke/pdoc_prep
Author: Andreas Paepcke
Author-email: paepcke@cs.stanford.edu
License: BSD
Keywords: pdoc,python documentation
Platform: UNKNOWN
